Speed_Testing_bot/__init__.py
speed_testing_bot-0.2.dist-info/METADATA
speed_testing_bot-0.2.dist-info/PKG-INFO.bak
speed_testing_bot-0.2.dist-info/WHEEL
speed_testing_bot-0.2.dist-info/top_level.txt
speed_testing_bot-0.2.dist-info/RECORD
